[
  {
    "chunk_id": "2004.06277_chunk_0",
    "arxiv_id": "2004.06277",
    "chunk_index": 0,
    "text": "A Demonstration of Issues with Value-Based Multiobjective\nReinforcement Learning Under Stochastic State Transitions\n\nPeter Vamplew\nFederation University Australia\nMt Helen, Victoria, Australia\n\nCameron Foale\nFederation University Australia\nMt Helen, Victoria, Australia\n\nRichard Dazeley\nDeakin University\nWaurn Ponds, Victoria, Australia\n\nABSTRACT\n\ntrue utility. As a result numerous non-linear scalarisation functions\nhave been explored in the literature (for example, [4, 23, 24]) –\nthese tend to produce algorithmic complications, but also may\nbetter represent the true preferences of the user. As well as the choice of scalarisation function and parameters, a\nsecond factor must be considered within this utility-based paradigm\n– the time-frame over which the utility is being maximised. Roijers\net al. [12] identified two distinct possibilities. The agent may aim to\nmaximise the expected scalarised return (ESR). That is, it is assumed\nthe returns are first scalarised, and then this agent aims for the\npolicy which maximises the expected value of that scalar. This\nESR approach is suited to problems where the aim is to maximise\nthe expected outcome within any individual episode. For example,\nwhen producing a treatment plan for a patient which trades off the\nlikelihood of a cure versus the extent of negative side-effects - any\nindividual patient will only undergo this treatment once, and so\nthey care about the utility obtained within that specific episode. In other contexts we may be concerned about the mean utility\nreceived over multiple episodes. In this situation the agent should\naim to maximise the scalarised expected return (SER) - that is, it\nestimates the expected vector return per episode, and then max-\nimises the scalarisation of that expected return. As demonstrated\nin Roijers et al. [11], the optimal policy for a particular MOMDP\nunder the ESR and SER setting may differ considerably, even if the\nsame scalarisation function and parameters are used in both cases. As noted by Roijers et al. [11] and Rădulescu et al. [10] much\nof the existing work in MORL has considered SER optimization,\nalthough this has often been implicit rather than explicitly stated. Much of this SER-focused work has been based on benchmark\nenvironments such as those of Vamplew et al. [18], the majority of\nwhich are deterministic MOMDPs. In this paper we demonstrate by example that the model-free\nvalue-based methods previously widely used in MORL research\nmay fail to maximise the SER utility when applied to MOMDPs\nwith stochastic state transitions. We report a previously unidentified issue with model-free, value-\nbased approaches to multiobjective reinforcement learning in the\ncontext of environments with stochastic state transitions. An ex-\nample multiobjective Markov Decision Process (MOMDP) is used\nto demonstrate that under such conditions these approaches may\nbe unable to discover the policy which maximises the Scalarised\nExpected Return, and in fact may converge to a Pareto-dominated\nsolution. We discuss several alternative methods which may be\nmore suitable for maximising SER in MOMDPs with stochastic\ntransitions.\n\narXiv:2004.06277v1 [cs.LG] 14 Apr 2020\n\nKEYWORDS\n\nmultiobjective reinforcement learning, multiobjective MDPs, sto-\nchastic MDPs\n\n1\nINTRODUCTION\n\nMultiobjective reinforcement learning (MORL) aims to extend the\ncapabilities of reinforcement learning (RL) methods to enable them\nto work for problems with multiple, conflicting objectives [12].",
    "word_count": 521,
    "char_count": 3486
  },
  {
    "chunk_id": "2004.06277_chunk_1",
    "arxiv_id": "2004.06277",
    "chunk_index": 1,
    "text": "An ex-\nample multiobjective Markov Decision Process (MOMDP) is used\nto demonstrate that under such conditions these approaches may\nbe unable to discover the policy which maximises the Scalarised\nExpected Return, and in fact may converge to a Pareto-dominated\nsolution. We discuss several alternative methods which may be\nmore suitable for maximising SER in MOMDPs with stochastic\ntransitions.\n\narXiv:2004.06277v1 [cs.LG] 14 Apr 2020\n\nKEYWORDS\n\nmultiobjective reinforcement learning, multiobjective MDPs, sto-\nchastic MDPs\n\n1\nINTRODUCTION\n\nMultiobjective reinforcement learning (MORL) aims to extend the\ncapabilities of reinforcement learning (RL) methods to enable them\nto work for problems with multiple, conflicting objectives [12]. RL algorithms generally assume that the environment is a Markov\nDecision Process (MDP) in which the agent is provided with a scalar\nreward after each action, and must aim to learn the policy which\nmaximises the long-term return based on those rewards. In contrast\nMORL algorithms operate within multiobjective MDPs (MOMDPs),\nin which the reward terms are vectors, with each element in the\nvector corresponding to a different objective. This creates a number\nof new issues to be addressed by the MORL agent. Most notably\nthere may be multiple policies which may be optimal (in terms of\nPareto optimality), and which policy the agent should learn is not\nimmediately obvious. In the utility-based paradigm of MORL [12, 29] it is assumed that\nthe preferences of the user can be defined in terms of a parame-\nterised utility function f , and that the aim of the agent should be to\nlearn the policy which produces vector returns which maximises\nthe utility to the user as defined by f . Various approaches have been explored for the form of the utility\nfunction – some may be better suited to express the preference of\nthe user within a particular problem domain, while others offer\nbenefits from an algorithmic perspective. A simple weighted linear\nscalarisation has been widely used because of its simplicity (for\nexample, [1, 3, 8]). Linear scalarisation transforms an MOMDP\ninto an equivalent single-objective MDP, and enables existing RL\napproaches to be directly applied [12]. However for many tasks this\nmay not be able to accurately represent the utility of the user, and so\nmay fail to discover the policy which is optimal with regards to their\n\n2\nSPACE TRADERS: AN EXAMPLE\nSTOCHASTIC MOMDP\n\nAs shown in Figure 1 the Space Traders MOMDP is a finite-horizon\ntask with a horizon of 2 time-steps. It consists of two non-terminal\nstates, with three actions available in each state. The agent starts at\nits home planet (state A) and must travel to another planet (state B)\nto deliver a shipment, and then return to State A with the payment. The agent receives a reward with two elements - the first is 0 on all\nactions, except that a reward of 1 is received when the agent suc-\ncessfully returns to state A, while the second element is a negative\nvalue reflecting the time taken to execute the action.\n\np=1.0; r=(0,‐12)\n\np=1.0; r=(1,‐10)\n\np=0.1; r=(0,‐1)\n\np=0.9; r=(0,‐6)\n\nA\nB\n\np=0.9; r=(1,‐8)\n\np=0.1; r=(0,‐7)\n\np=0.85; r=(0,0)\np=0.15; r=(0,0)\n\np=0.15; r=(0,0)\n\np=0.85; r=(1,0)\n\nFigure 1: The Space Traders MOMDP.",
    "word_count": 523,
    "char_count": 3246
  },
  {
    "chunk_id": "2004.06277_chunk_2",
    "arxiv_id": "2004.06277",
    "chunk_index": 2,
    "text": "The agent receives a reward with two elements - the first is 0 on all\nactions, except that a reward of 1 is received when the agent suc-\ncessfully returns to state A, while the second element is a negative\nvalue reflecting the time taken to execute the action.\n\np=1.0; r=(0,‐12)\n\np=1.0; r=(1,‐10)\n\np=0.1; r=(0,‐1)\n\np=0.9; r=(0,‐6)\n\nA\nB\n\np=0.9; r=(1,‐8)\n\np=0.1; r=(0,‐7)\n\np=0.85; r=(0,0)\np=0.15; r=(0,0)\n\np=0.15; r=(0,0)\n\np=0.85; r=(1,0)\n\nFigure 1: The Space Traders MOMDP. Solid black lines show the Direct actions, solid grey lines show the Indirect actions, and\ndashed lines indicate Teleport actions. Sold black circles indicate terminal (failure) states. Reward\non\nsuccess\n\nReward\non\nfailure\n\nPolicy\nidentifier\n\nAction in\nstate A\n\nAction in\nstate B\nMean return\n\nMean\nreward\n\nState\nAction\nP(success)\n\nII\nIndirect\nIndirect\n(1, -22)\nID\nIndirect\nDirect\n(0.9, -19.9)\nIT\nIndirect\nTeleport\n(0.85, -12)\nDI\nDirect\nIndirect\n(0.9, -14.5)\nDD\nDirect\nDirect\n(0.81, -12.61)\nDT\nDirect\nTeleport\n(0.765, -5.5)\nTI\nTeleport\nIndirect\n(0.85, -8.5)\nTD\nTeleport\nDirect\n(0.765, -6.715)\nTT\nTeleport\nTeleport\n(0.7225, 0)\nTable 2: The mean episodic return vector for each of the\nnine deterministic policies available for the Space Traders\nMOMDP. Indirect\n1.0\n(0,-12)\nn/a\n(0,-12)\nDirect\n0.9\n(0, -6)\n(0, -1)\n(0, -5.5)\nTeleport\n0.85\n(0,0)\n(0,0)\n(0, 0)\n\nA\n\nIndirect\n1.0\n(1, -10)\nn/a\n(1, -10)\nDirect\n0.9\n(1, -8)\n(0, -7)\n(0.9, -7.9)\nTeleport\n0.85\n(1, 0)\n(0, 0)\n(0.85, 0)\nTable 1: The probability of success and reward values for\neach state-action pair in the Space Traders MOMDP. B\n\nThere are three possible pathways between the two planets. The direct path (actions shown by solid black lines in Figure 1)\nis fairly short, but there is a risk of the agent being waylaid by\nspace pirates and failing to complete the task. The indirect path\n(grey lines) avoids the pirates and so always leads to successful\ncompletion of the mission, but takes longer. Finally the recently\ndeveloped teleportation system (dashed lines) allows instantaneous\ntransportation, but has a higher risk of failure. The figure also\ndetails the probability of success, and the reward for the mission-\nsuccess and time objectives for each action – due to variations in\nlocal conditions such as solar winds and the location of the space\npirates, the time values for the outward and return journeys on a\nparticular path may vary. Table 1 summarises the transition probabilities and rewards of\nthe MOMDP, and also shows the mean immediate reward for each\naction from each state, weighted by the probability of success. As there are three actions from each state there are a total of nine\ndeterministic policies available to the agent. The mean reward per\nepisode for each of these policies is shown in Table 2 and illustrated\nin Figure 2. The solid points in the figure highlight the policies\nwhich belong to the Pareto front, and the dashed grey line indicates\nthe convex hull (only those policies lying on the convex hull can be\n\nlocated via methods using linear scalarisation – this set of policies\nis referred to as the Convex Coverage Set [13]).",
    "word_count": 514,
    "char_count": 3088
  },
  {
    "chunk_id": "2004.06277_chunk_3",
    "arxiv_id": "2004.06277",
    "chunk_index": 3,
    "text": "The mean reward per\nepisode for each of these policies is shown in Table 2 and illustrated\nin Figure 2. The solid points in the figure highlight the policies\nwhich belong to the Pareto front, and the dashed grey line indicates\nthe convex hull (only those policies lying on the convex hull can be\n\nlocated via methods using linear scalarisation – this set of policies\nis referred to as the Convex Coverage Set [13]). For the remainder of the paper we will assume that the agent’s\naim is to minimise the time taken to complete the delivery and\nreturn to A, subject to having at least an 88% probability of suc-\ncessful completion. That is, the scalarisation function f (®v) = v2\nif v1 > 0.88 and −∞otherwise. The optimal policy for this aim is\nto follow the direct path to B and then the indirect path back to A\n(policy DI).\n\n3\nAPPLYING MODEL-FREE VALUE-BASED\nMORL METHODS TO SPACE TRADERS\n\nIn this section we will discuss how some of the value-based MORL\nmethods previously used in the literature would perform on the\nSpace Traders MOMDP. All the methods discussed are assumed to\nbe based on a multiobjective extension of model-free value-based\nRL algorithms such as Q-Learning or SARSA – for example see [25,\np. 3668]. For the purposes of this section we will restrict discussion\nto single-policy methods in which the scalarisation function f is\n\n2\n\n0\n\nAction in state A\nPolicy\nQ(A, a)\nIndirect\nID\n(0.9, -19.9)\nDirect\nDD\n(0.81, -12.61)\nTeleport\nTD\n(0.765, -6.715)\nTable 3: The Q-values which will be learned for each action\nin state A, under the assumption that the Direct action will\nbe selected in State B. TT\n\n‐5\n\nDT\n\nTD\n\nTime penalty\n\nTI\n\n‐10\n\nDD\n\nIT\n\n‐15\n\nDI\n\n‐20\n\nID\n\nII\n\n‐25\n\n0.7\n0.75\n0.8\n0.85\n0.9\n0.95\n1\n\nonly on the current state of the environment, but also on rewards\nreceived so far by the agent during this episode [5, 11]. That is, if the\nscalarisation function is f then at time k the agent will select the ac-\ntion a which maximises the value of f (Q(sk,a, Ík\nt=1 rt ) + Ík\nt=1 rt ). For the purposes of the following discussion we will assume that\nf is the thresholded lexicographic ordering operator (TLO) [4, 6],\nand that a thresholding parameter of 0.88 is applied to the first\nelement of the Q-value vector. The intention here is to maximise\nthe value of the second objective (i.e. minimise time), subject to\nachieving the threshold level for the first objective. If this operator\ncould be applied directly to the mean returns of each policy from\nTable 2, then clearly policy DI would be selected. However if we consider how the TLO operator selects actions\nduring the execution of a policy, then a different result will emerge. Regardless of the path selected at state A, if state B is successfully\nreached then a zero reward will have been received by the agent. Therefore the choice of action at state B is independent of the\nprevious action.",
    "word_count": 514,
    "char_count": 2866
  },
  {
    "chunk_id": "2004.06277_chunk_4",
    "arxiv_id": "2004.06277",
    "chunk_index": 4,
    "text": "If this operator\ncould be applied directly to the mean returns of each policy from\nTable 2, then clearly policy DI would be selected. However if we consider how the TLO operator selects actions\nduring the execution of a policy, then a different result will emerge. Regardless of the path selected at state A, if state B is successfully\nreached then a zero reward will have been received by the agent. Therefore the choice of action at state B is independent of the\nprevious action. Looking at the mean action values reported in\nTable 1, it can be seen that action T will be eliminated as it fails to\nmeet the threshold for the first objective, and that action D will be\npreferred over I as both meet the threshold, and D has a superior\nvalue for the time objective. So it can already be seen that this agent\nwill not converge to the desired policy DI. Knowing that action D will be selected at state B, we can calculate\nthe Q-values for each action at state A, as shown in Table 3. The TLO\naction selector will eliminate actions D and T from consideration\nas neither meets the threshold of 0.88 for the probability of success. Action I will be selected giving rise to the overall policy ID. Not\nonly is this not the desired DI policy, but as is evident from Figure\n2 its average outcome is in fact Pareto-dominated by DI. Probability of mission success\n\nFigure 2: The mean return per episode for the nine possible\ndeterministic policies for the Space Traders MOMDP. Each\npolicy’s return is labelled with a bigram specifying its ac-\ntions. I, D, T refer to the indirect, direct and teleport actions\nso, for example, policy DI selects the direct action in state\nA and the indirect action in state B. Solid markers indicate\npolicies which are members of the Pareto-front, and hol-\nlow markers indicate dominated policies. The dashed grey\nlines illustrate the convex hull formed by mixture combina-\ntions of the policies which make up the Convex Coverage\nSet (CCS). The dashed red vertical line indicates the thresh-\nold value of 0.88 for the probability of mission success, and\nthe red square marker is the DI policy which is optimal for\nthat setting of the threshold.\n\nused to filter the multiple Pareto-optimal policies which may be\navailable so as to obtain a single policy which is optimal with\nregards to f . Multiple-policy MORL methods will be discussed in\nSection 5. All methods learn vector-valued estimated Q-values, but differ\nin terms of the scalarisation or ordering method used to perform\naction-selection, and the characteristics on which the Q-value and\npolicy are conditioned.\n\n3.1\nLinear scalarisation\n\nA simple approach to MORL is to apply a linear weighted scalari-\nsation to the elements of the Q-value vector prior to selecting the\ngreedy action. As mentioned earlier, this converts the MOMDP into\nan equivalent MDP, and so the Q-values and action-selection need\nonly be conditioned on the current state of the MDP. However it is\nwell-known that methods using linear scalarisation are unable to\nidentify solutions which do not lie on the convex hull of the Pareto\nfront [22].",
    "word_count": 535,
    "char_count": 3094
  },
  {
    "chunk_id": "2004.06277_chunk_5",
    "arxiv_id": "2004.06277",
    "chunk_index": 5,
    "text": "All methods learn vector-valued estimated Q-values, but differ\nin terms of the scalarisation or ordering method used to perform\naction-selection, and the characteristics on which the Q-value and\npolicy are conditioned.\n\n3.1\nLinear scalarisation\n\nA simple approach to MORL is to apply a linear weighted scalari-\nsation to the elements of the Q-value vector prior to selecting the\ngreedy action. As mentioned earlier, this converts the MOMDP into\nan equivalent MDP, and so the Q-values and action-selection need\nonly be conditioned on the current state of the MDP. However it is\nwell-known that methods using linear scalarisation are unable to\nidentify solutions which do not lie on the convex hull of the Pareto\nfront [22]. Clearly from Figure 2 this is the case for policy DI, and\nso linear methods will not be able to converge to this policy. This\nresult is not surprising and we mention it here simple for the sake\nof completeness.\n\n4\nTHE INTERACTION OF LOCAL\nDECISION-MAKING AND STOCHASTIC\nSTATE TRANSITIONS\n\nThe failure of the non-linear value-based MORL algorithms on\nthe Space Traders MOMDP can be explained by the analysis of\nstochastic-transition MOMDPs previously carried out by Bryce\net al. [2] in the context of probabilistic planning. This analysis has\nbeen largely overlooked by MORL researchers so far, and so one of\nthe contributions of this paper is to bring this work to the attention\nof the MORL research community. Figure 3 illustrates a simple MDP reproduced from Bryce et al.\n[2], with a stochastic branch occurring on the transition from the\ninitial state. The table in the lower half of this figure specifies the\nmean return for the four possible deterministic policies. Keeping\nin mind that this MOMDP is phrased in terms of minising cost\n\n3.2\nNon-linear scalarisation\n\nA variety of non-linear scalarisation methods have been explored in\nthe MORL literature [4, 23, 24]. The non-linear nature of the scalari-\nsation function means that the assumption of additivity underlying\nthe Bellman equation no longer applies. In order to deal with this,\nboth the choice of action and the Q-values must be conditioned not\n\n3\n\nPr(G|S1) = 1.0\nE[Cost(S1)] = 50\nPr(G|S2) = 0.5\nE[Cost(S2)] = 10\n\nThis requirement is fundamentally incompatible with the lo-\ncalised decision-making at the heart of model-free value-based RL\nmethods like Q-learning, where it is assumed that the correct choice\nof action can be determined purely based on information available\nto the agent at the current state. The provision of additional infor-\nmation such as the sum of rewards received so far in the episode as\ndiscussed in Section 3.2 is insufficient, as it still only provides infor-\nmation about the branch which has been followed in this episode,\nrather than all possible branches which might have been executed. The conclusion to be drawn from both this example and Space\nTraders is that value-based model-free MORL methods are inher-\nently limited when applied in the context of SER optimisation of\nnon-linear utility on MOMDPs with non-deterministic state transi-\ntions. These methods may fail to discover the policy which max-\nimises the SER (i.e. the mean utility over multiple episodes).",
    "word_count": 518,
    "char_count": 3189
  },
  {
    "chunk_id": "2004.06277_chunk_6",
    "arxiv_id": "2004.06277",
    "chunk_index": 6,
    "text": "The provision of additional infor-\nmation such as the sum of rewards received so far in the episode as\ndiscussed in Section 3.2 is insufficient, as it still only provides infor-\nmation about the branch which has been followed in this episode,\nrather than all possible branches which might have been executed. The conclusion to be drawn from both this example and Space\nTraders is that value-based model-free MORL methods are inher-\nently limited when applied in the context of SER optimisation of\nnon-linear utility on MOMDPs with non-deterministic state transi-\ntions. These methods may fail to discover the policy which max-\nimises the SER (i.e. the mean utility over multiple episodes). To\nthe best of our knowledge this limitation has not previously been\nidentified in the MORL literature. It is particularly important as\nthe combination of SER, stochastic state transitions and non-linear\nutility may well arise in important areas of application such as AI\nsafety [20]. Pr(G|S3) = 0.75\nE[Cost(S3)] = 30\n\nS1\n\nPr(G|S4) = 0.0\nE[Cost(S4)] = 0\n\nS3\n\nS2\n\nPr(G)\n\nS1\n\nPr(G)\n\nS4\n\nS2\n\nS3\n\nS4\n\nb1\nb2\n\nE[Cost]\n\n0.2\n0.8\na\n\nE[Cost]\n\nPr(G)\n\na,[S1| S3]\n\na,[S2|S3]\n\na,[S1| S4]\na,[S2| S4]\n\nbI\n\nE[Cost]\n\nPlans π\nE[Cost(π)]\nPr(G|π)\na, [π1|π3]\n1+(.2)50+(.8)30 = 35\n(.2)1+(.8).75 = .8\na, [π2|π3]\n1+(.2)10+(.8)30 = 27\n(.2).5+(.8).75 = .7\na, [π1|π4]\n1+(.2)50+(.8)0 = 11\n(.2)1+(.8)0\n= .2\na, [π2|π4]\n1+(.2)10+(.8)0 = 3\n(.2).5+(.8)0\n= .1\n\n5\nPOTENTIAL SOLUTIONS\n\nIn this section we will briefly review and critique various options\nwhich may address the issue identified above. Figure 3: A sample probabilistic planning MOMDP, repro-\nduced from Bryce et al. [2]. Executing action a from bt leads\nto two branches with probability 0.2 and 0.8. At each of these\nbranches a choice between two sub-plans with different pay-\noffs exists. The aim for the planner is to identify the correct\nsub-plan to execute at each branch, so as to minimise cost\nwhile ensuring successful execution above a fixed probabil-\nity.\n\n5.1\nESR Optimisation\n\nAs noted earlier the issue described arises due to the fact that an\nagent aiming to find a policy optimal with regards to SER must\ntake into account the value which will be received on average by\nits policy across multiple episodes. Framing the problem in terms\nof ESR optimisation would eliminate this issue. However ESR is\nclearly inappropriate for the context of the Space Traders MOMDP. The agent will aim to ensure every episode meets the threshold\nfor the mission-success objective. This can only be achieved by\nfollowing the strictly safe II policy, which produces results which\nare far worse for the user’s true utility than the DI policy.\n\n(rather than maximising the inverse of the cost), it can be seen that\nunlike Space Traders, there are no Pareto-dominated policies for\nthis MOMDP.1. The aim of the agent is to minimise the cost, subject to satisfying\nat least a 0.6 probability of success. Within an ESR formulation of the\nproblem (i.e. ensure the probability of success threshold is achieved\nin each episode), the optimal policy is to select sub-plan π1 at branch\nb1 and π3 at branchb2 as both of these sub-plans individually satisfy\nthe probability threshold.",
    "word_count": 527,
    "char_count": 3181
  },
  {
    "chunk_id": "2004.06277_chunk_7",
    "arxiv_id": "2004.06277",
    "chunk_index": 7,
    "text": "The aim of the agent is to minimise the cost, subject to satisfying\nat least a 0.6 probability of success. Within an ESR formulation of the\nproblem (i.e. ensure the probability of success threshold is achieved\nin each episode), the optimal policy is to select sub-plan π1 at branch\nb1 and π3 at branchb2 as both of these sub-plans individually satisfy\nthe probability threshold. However if considered from the SER\nperspective, the optimal plan is to execute π2 at branch b1 and π3 at\nbranch b2 – while π2 itself fails to achieve the probability threshold,\nthis branch is executed with a low probability and so the mean\noutcome of the two sub-plans will achieve the threshold while also\nproducing a significant cost saving. As identified by [2], whether the overall policy meets the con-\nstraints depends on the probability with which each branch is exe-\ncuted as well as the mean outcome of each branch. Determining the\ncorrect sub-plan to follow at each branch requires consideration of\nthe sub-plan options available at each other branch in combination\nwith the probability of branch execution.\n\n5.2\nNon-stationary or non-deterministic\npolicies\n\nPrevious work has demonstrated that for the SER formulation,\nor for non-episodic tasks, policies formed from a non-stationary\nor non-deterministic mixture of deterministic policies can Pareto-\ndominate deterministic policies [17, 21]. For example, a mixture\nwhich randomly selects between policies TI and II with appropri-\nate probabilities at the start of each episode can produce a mean\noutcome which exceeds that of policy DI, as shown in Figure 4 –\nthe mixture policy which selects TI with probability 0.65 and II\nwith probability 0.35 achieves a mean return of (0.9025, -13.225)\nwhich is superior to the deterministic DI policy with regards to\nboth objectives. However the use of policies which vary so widely may not be\nappropriate in all contexts – for many problems the more consistent\noutcome produced by a deterministic policy may be preferable, and\nso methods to find SER-optimal deterministic policies for stochastic\nMOMDPs are still required.\n\n1While clearly illustrating the problem, this MOMDP also lacks the narrative drama of\nSpace Traders!\n\n4\n\n‐7\n\naware of any prior work which has attempted to do so. However the\nmodel-based MORL approach proposed in Wiering et al. [28] may\nprovide a suitable basis for implementing a reinforcement learning\nequivalent of MOLAO*. TI\n\n‐9\n\n‐11\n\nIT\n0.65TI, 0.35II\n\nTime penalty\n\n‐13\n\n‐15\n\nDI\n\n5.5\nPolicy-search methods\n\n‐17\n\nAn alternative to value-based approaches is to use policy-search\napproaches to RL. As these directly maximise the policy as a whole\nas defined by a set of policy parameters, they do not have the local\ndecision-making issue faced by model-free value-based methods. Multiple researchers have proposed and evaluated policy-search\nmethods for multiobjective problems [7, 9, 15, 16]. One issue to be\naddressed however is that these methods most naturally produce\nstochastic policies and as such may have the same problems as\nfaced by the mixture or non-stationary approaches discussed in\nSection 5.2, unless they are modified or constrained so as to ensure\nconvergence to a deterministic policy.\n\n‐19\n\nID\n\n‐21\n\nII\n\n‐23\n\n0.85\n0.87\n0.89\n0.91\n0.93\n0.95\n0.97\n0.99\n\nProbability of mission success\n\nFigure 4: The mean return per episode for a mixture pol-\nicy formed by selecting between the deterministic policies\nTI and II with probability 0.65 and 0.35 respectively Pareto-\ndominates the mean return of deterministic policy DI.\n\n5.3\nMulti-policy value-based MORL\n\n6\nCONCLUSION\n\nAs well as the single-policy value-based MORL methods examined\nin this paper, several authors have proposed multi-policy methods.",
    "word_count": 591,
    "char_count": 3722
  },
  {
    "chunk_id": "2004.06277_chunk_8",
    "arxiv_id": "2004.06277",
    "chunk_index": 8,
    "text": "One issue to be\naddressed however is that these methods most naturally produce\nstochastic policies and as such may have the same problems as\nfaced by the mixture or non-stationary approaches discussed in\nSection 5.2, unless they are modified or constrained so as to ensure\nconvergence to a deterministic policy.\n\n‐19\n\nID\n\n‐21\n\nII\n\n‐23\n\n0.85\n0.87\n0.89\n0.91\n0.93\n0.95\n0.97\n0.99\n\nProbability of mission success\n\nFigure 4: The mean return per episode for a mixture pol-\nicy formed by selecting between the deterministic policies\nTI and II with probability 0.65 and 0.35 respectively Pareto-\ndominates the mean return of deterministic policy DI.\n\n5.3\nMulti-policy value-based MORL\n\n6\nCONCLUSION\n\nAs well as the single-policy value-based MORL methods examined\nin this paper, several authors have proposed multi-policy methods. These operate by retaining multiple value vectors at each state. These can correspond to either all Pareto-optimal values obtainable\nfrom that state, or (for purposes of efficiency) be constrained to\nstore only those values which can help construct the optimal value\nfunction under some assumptions about the nature of the overall\nutility function f [13]. Multi-policy algorithms were first proposed\nfor variants of dynamic programming [26, 27] and more recently\nhave been extended to MORL [14, 25]. By propagating back the coverage set of values available at each\nsuccessor state, these algorithms would correctly identify all poten-\ntially optimal policies available at the starting state, and the optimal\npolicy could then be selected at that point – in the context of Space\nTraders this would allow for the desired DI policy to be selected. However two issues still need to be addressed. One is ensuring\nthat the agent has a means of determining which action should\nbe performed in each encountered state to align with the initial\nchoice of policy. Existing algorithms do not necessarily provide\nsuch a means in the context of stochastic transitions. Second, the\nexisting multi-policy MORL algorithms do not have an obvious\nextension to complex state-spaces where tabular methods are in-\nfeasible. Conventional function-approximation methods can not\nbe applied, as the cardinality of the vectors to be stored can vary\nbetween states. Vamplew et al. [19] provides preliminary work ad-\ndressing this problem, but further work is still required to make\nthis approach practical. We have described a stochastic MOMDP and utility function which,\ndespite their seeming simplicity, are not amenable to solution by the\nwidely-used model-free value-based approaches to MORL. While\nthis issue with MOMDPs with stochastic state transitions has pre-\nviously been described in the context of probabilistic planning [2],\nthis is the first work to identify the implications for MORL. Our\nexample also demonstrates that under stochastic state-transitions,\nit is in fact possible for such MORL methods to converge to a Pareto-\ndominated policy. The combination of SER optimisation, stochastic state transi-\ntions and the need for a deterministic policy are likely to arise\nin a range of applications (particularly in risk-aware agents), and\nso awareness of the limitations of some MORL methods to work\nunder these characteristics is important in order to avoid the use\nof inappropriate methods.",
    "word_count": 514,
    "char_count": 3301
  },
  {
    "chunk_id": "2004.06277_chunk_9",
    "arxiv_id": "2004.06277",
    "chunk_index": 9,
    "text": "Our\nexample also demonstrates that under stochastic state-transitions,\nit is in fact possible for such MORL methods to converge to a Pareto-\ndominated policy. The combination of SER optimisation, stochastic state transi-\ntions and the need for a deterministic policy are likely to arise\nin a range of applications (particularly in risk-aware agents), and\nso awareness of the limitations of some MORL methods to work\nunder these characteristics is important in order to avoid the use\nof inappropriate methods. REFERENCES\n\n[1] Leon Barrett and Srini Narayanan. 2008. Learning all optimal policies with\nmultiple criteria. In Proceedings of the 25th international conference on Machine\nlearning. 41–47.\n[2] Daniel Bryce, William Cushing, and Subbarao Kambhampati. 2007. Probabilistic\nplanning is multi-objective. Arizona State University, Tech. Rep. ASU-CSE-07-006\n(2007).\n[3] A Castelletti, Stefano Galelli, Marcello Restelli, and Rodolfo Soncini-Sessa. 2010. Tree-based reinforcement learning for optimal water reservoir operation. Water\nResources Research 46, 9 (2010).\n[4] Zoltán Gábor, Zsolt Kalmár, and Csaba Szepesvári. 1998. Multi-criteria reinforce-\nment learning.. In ICML, Vol. 98. 197–205.\n[5] Peter Geibel. 2006. Reinforcement learning for MDPs with constraints. In Euro-\npean Conference on Machine Learning. Springer, 646–653.\n[6] Rustam Issabekov and Peter Vamplew. 2012. An empirical comparison of two\ncommon multiobjective reinforcement learning algorithms. In Australasian Joint\nConference on Artificial Intelligence. Springer, 626–636.\n[7] Simone Parisi, Matteo Pirotta, and Jan Peters. 2017. Manifold-based multi-\nobjective policy search with sample reuse. Neurocomputing 263 (2017), 3–14.\n[8] Julien Perez, Cécile Germain-Renaud, Balázs Kégl, and Charles Loomis. 2009. Responsive elastic computing. In Proceedings of the 6th international conference\nindustry session on Grids meets autonomic computing. 55–64.\n[9] Matteo Pirotta, Simone Parisi, and Marcello Restelli. 2015. Multi-objective rein-\nforcement learning with continuous Pareto frontier approximation. In Twenty-\nNinth AAAI Conference on Artificial Intelligence.\n[10] Roxana Rădulescu, Patrick Mannion, Diederik M Roijers, and Ann Nowé. 2019. Equilibria in multi-objective games: A utility-based perspective. In Proceedings of\nthe adaptive and learning agents workshop (ALA-19) at AAMAS.\n\n5.4\nModel-based methods\n\nAs well as describing the difficulties faced by probabilistic plan-\nning, Bryce et al. [2] also propose a search algorithm known as\nMultiobjective Looping AO* (MOLAO*) to solve such tasks. As a\nplanning method, this assumes an MOMDP with known state tran-\nsition probabilities and a finite and tractable number of discrete\nstates. It may be possible to extend this approach by integrating it\nwithin model-based RL algorithms which can learn to estimate the\ntransition probabilities and to generalise across states. We are not\n\n5\n\n[11] Diederik M Roijers, Denis Steckelmacher, and Ann Nowé. 2018. Multi-objective\nreinforcement learning for the expected utility of the return. In Adaptive Learning\nAgents (ALA) workshop at AAMAS, Vol. 18.\n[12] Diederik M Roijers, Peter Vamplew, Shimon Whiteson, and Richard Dazeley. 2013. A survey of multi-objective sequential decision-making. Journal of Artificial\nIntelligence Research 48 (2013), 67–113.\n[13] Diederik M Roijers, Shimon Whiteson, and Frans A Oliehoek. 2013. Computing\nconvex coverage sets for multi-objective coordination graphs. In International\nConference on Algorithmic DecisionTheory. Springer, 309–323.\n[14] Manuela Ruiz-Montiel, Lawrence Mandow, and José-Luis Pérez-de-la Cruz. 2017. A temporal difference method for multi-objective reinforcement learning. Neuro-\ncomputing 263 (2017), 15–25.\n[15] Christian Robert Shelton. 2001.",
    "word_count": 519,
    "char_count": 3778
  },
  {
    "chunk_id": "2004.06277_chunk_10",
    "arxiv_id": "2004.06277",
    "chunk_index": 10,
    "text": "A survey of multi-objective sequential decision-making. Journal of Artificial\nIntelligence Research 48 (2013), 67–113.\n[13] Diederik M Roijers, Shimon Whiteson, and Frans A Oliehoek. 2013. Computing\nconvex coverage sets for multi-objective coordination graphs. In International\nConference on Algorithmic DecisionTheory. Springer, 309–323.\n[14] Manuela Ruiz-Montiel, Lawrence Mandow, and José-Luis Pérez-de-la Cruz. 2017. A temporal difference method for multi-objective reinforcement learning. Neuro-\ncomputing 263 (2017), 15–25.\n[15] Christian Robert Shelton. 2001. Importance sampling for reinforcement learning\nwith multiple objectives. (2001).\n[16] Eiji Uchibe and Kenji Doya. 2007. Constrained reinforcement learning from\nintrinsic and extrinsic rewards. In 2007 IEEE 6th International Conference on\nDevelopment and Learning. IEEE, 163–168.\n[17] Peter Vamplew, Richard Dazeley, Ewan Barker, and Andrei Kelarev. 2009. Con-\nstructing stochastic mixture policies for episodic multiobjective reinforcement\nlearning tasks. In Australasian joint conference on artificial intelligence. Springer,\n340–349.\n[18] Peter Vamplew, Richard Dazeley, Adam Berry, Rustam Issabekov, and Evan\nDekker. 2011. Empirical evaluation methods for multiobjective reinforcement\nlearning algorithms. Machine learning 84, 1-2 (2011), 51–80.\n[19] Peter Vamplew, Richard Dazeley, Cameron Foale, and Tanveer Choudhury. 2018. Non-functional regression: A new challenge for neural networks. Neurocomputing\n314 (2018), 326–335.\n[20] Peter Vamplew, Richard Dazeley, Cameron Foale, Sally Firmin, and Jane Mum-\nmery. 2018. Human-aligned artificial intelligence is a multiobjective problem. Ethics and Information Technology 20, 1 (2018), 27–40.\n[21] Peter Vamplew, Rustam Issabekov, Richard Dazeley, Cameron Foale, Adam Berry,\nTim Moore, and Douglas Creighton. 2017. Steering approaches to Pareto-optimal\nmultiobjective reinforcement learning. Neurocomputing 263 (2017), 26–38.\n[22] Peter Vamplew, John Yearwood, Richard Dazeley, and Adam Berry. 2008. On\nthe limitations of scalarisation for multi-objective reinforcement learning of\npareto fronts. In Australasian Joint Conference on Artificial Intelligence. Springer,\n372–378.\n[23] Kristof Van Moffaert, Madalina M Drugan, and Ann Nowé. 2013. Hypervolume-\nbased multi-objective reinforcement learning. In International Conference on\nEvolutionary Multi-Criterion Optimization. Springer, 352–366.\n[24] Kristof Van Moffaert, Madalina M Drugan, and Ann Nowé. 2013. Scalarized\nmulti-objective reinforcement learning: Novel design techniques. In 2013 IEEE\nSymposium on Adaptive Dynamic Programming and Reinforcement Learning (AD-\nPRL). IEEE, 191–199.\n[25] Kristof Van Moffaert and Ann Nowé. 2014. Multi-objective reinforcement learning\nusing sets of pareto dominating policies. The Journal of Machine Learning Research\n15, 1 (2014), 3483–3512.\n[26] DJ White. 1982. Multi-objective infinite-horizon discounted Markov decision\nprocesses. Journal of mathematical analysis and applications 89, 2 (1982), 639–647.\n[27] Marco A Wiering and Edwin D De Jong. 2007. Computing optimal stationary\npolicies for multi-objective markov decision processes. In 2007 IEEE International\nSymposium on Approximate Dynamic Programming and Reinforcement Learning. IEEE, 158–165.\n[28] Marco A Wiering, Maikel Withagen, and Mădălina M Drugan. 2014. Model-based\nmulti-objective reinforcement learning. In 2014 IEEE Symposium on Adaptive\nDynamic Programming and Reinforcement Learning (ADPRL). IEEE, 1–6.\n[29] Luisa M Zintgraf, Timon V Kanters, Diederik M Roijers, Frans Oliehoek, and\nPhilipp Beau. 2015. Quality assessment of MORL algorithms: A utility-based\napproach. In Benelearn 2015: Proceedings of the 24th Annual Machine Learning\nConference of Belgium and the Netherlands.\n\n6",
    "word_count": 483,
    "char_count": 3768
  }
]